manm_cs/__init__.py
manm_cs/__main__.py
manm_cs/utils.py
manm_cs/graph/__init__.py
manm_cs/graph/graph.py
manm_cs/graph/graph_builder.py
manm_cs/noise/__init__.py
manm_cs/noise/continous_noise.py
manm_cs/noise/discrete_noise.py
manm_cs/noise/discrete_noise_builder.py
manm_cs/noise/gaussian_noise_builder.py
manm_cs/noise/noise.py
manm_cs/prob_distributions/__init__.py
manm_cs/prob_distributions/prob_distribution.py
manm_cs/prob_distributions/continuous/__init__.py
manm_cs/prob_distributions/continuous/bimodal_distribution.py
manm_cs/prob_distributions/continuous/continuous_distribution.py
manm_cs/prob_distributions/continuous/gaussian_distribution.py
manm_cs/prob_distributions/discrete/__init__.py
manm_cs/prob_distributions/discrete/binomial_distribution.py
manm_cs/prob_distributions/discrete/custom_discrete_distribution.py
manm_cs/prob_distributions/discrete/discrete_distribution.py
manm_cs/prob_distributions/discrete/random_discrete_distribution.py
manm_cs/prob_distributions/discrete/uniform_discrete_distribution.py
manm_cs/variables/__init__.py
manm_cs/variables/continuous_variable.py
manm_cs/variables/discrete_variable.py
manm_cs/variables/variable.py
manm_cs/variables/variable_type.py
test/__init__.py
test/test_manm_cs.py
test/test_manm_cs_pypi.py
test/graph/__init__.py
test/graph/test_graph.py
manm_cs-0.1.7.dist-info/LICENSE
manm_cs-0.1.7.dist-info/METADATA
manm_cs-0.1.7.dist-info/WHEEL
manm_cs-0.1.7.dist-info/top_level.txt
manm_cs-0.1.7.dist-info/RECORD
