Metadata-Version: 2.1
Name: manm-cs
Version: 0.1.7
Summary: Data generation for causal structure learning based on mixed additive noise model (MANM)
Home-page: https://github.com/hpi-epic/manm-cs
Author: Johannes Huegle, Christopher Hagedorn, Lukas Boehme, Mats Poerschke, Jonas Umland
Author-email: johannes.huegle@hpi.de
Project-URL: Bug Tracker, https://github.com/hpi-epic/manm-cs/issues
Classifier: Programming Language :: Python :: 3
Classifier: License :: OSI Approved :: MIT License
Classifier: Operating System :: OS Independent
Requires-Python: >=3.6
License-File: LICENSE
Requires-Dist: pandas (>=1.1.5)
Requires-Dist: numpy (>=1.19.5)
Requires-Dist: multiprocess (>=0.70.11.1)
Requires-Dist: validation (==0.5.0)
Requires-Dist: networkx (>=2.5)
Requires-Dist: pathos (>=0.2.7)
Requires-Dist: scipy (>=1.10.0)
